{
    "classes": [
        {
            "className": "MainThread",
            "object": true,
            "qualifiedClassName": "MainThread",
            "slots": [
                {
                    "access": "private",
                    "arguments": [
                        {
                            "name": "func",
                            "type": "std::function<void()>"
                        }
                    ],
                    "name": "mainThreadSlot",
                    "returnType": "void"
                }
            ],
            "superClasses": [
                {
                    "access": "public",
                    "name": "QObject"
                }
            ]
        }
    ],
    "inputFile": "MainThread.h",
    "outputRevision": 68
}
